odoo8_addon_l10n_ar_retentions_basic-8.0.1.0.0-py2.7-nspkg.pth
odoo_addons/l10n_ar_retentions_basic/.gitignore
odoo_addons/l10n_ar_retentions_basic/__openerp__.py
odoo_addons/l10n_ar_retentions_basic/retention.py
odoo_addons/l10n_ar_retentions_basic/account_voucher.py
odoo_addons/l10n_ar_retentions_basic/retention_data.xml
odoo_addons/l10n_ar_retentions_basic/__init__.py
odoo_addons/l10n_ar_retentions_basic/voucher_payment_receipt_view.xml
odoo_addons/l10n_ar_retentions_basic/retention_view.xml
odoo_addons/l10n_ar_retentions_basic/security/ir.model.access.csv
odoo_addons/l10n_ar_retentions_basic/migrations/8.0.1.0/pre-migration.py
odoo_addons/l10n_ar_retentions_basic/migrations/8.0.1.0/post-migration.py
odoo_addons/l10n_ar_retentions_basic/i18n/es_AR.po
odoo_addons/l10n_ar_retentions_basic/i18n/es_AR.mo
odoo_addons/l10n_ar_retentions_basic/i18n/l10n_ar_retentions_basic.pot
odoo8_addon_l10n_ar_retentions_basic-8.0.1.0.0.dist-info/top_level.txt
odoo8_addon_l10n_ar_retentions_basic-8.0.1.0.0.dist-info/WHEEL
odoo8_addon_l10n_ar_retentions_basic-8.0.1.0.0.dist-info/RECORD
odoo8_addon_l10n_ar_retentions_basic-8.0.1.0.0.dist-info/metadata.json
odoo8_addon_l10n_ar_retentions_basic-8.0.1.0.0.dist-info/DESCRIPTION.rst
odoo8_addon_l10n_ar_retentions_basic-8.0.1.0.0.dist-info/METADATA
odoo8_addon_l10n_ar_retentions_basic-8.0.1.0.0.dist-info/namespace_packages.txt
